streamlit_session_memo/__init__.py
streamlit_session_memo/_version.py
streamlit_session_memo/session_memo.py
streamlit_session_memo-0.3.2.dist-info/METADATA
streamlit_session_memo-0.3.2.dist-info/WHEEL
streamlit_session_memo-0.3.2.dist-info/licenses/LICENSE
streamlit_session_memo-0.3.2.dist-info/RECORD
