Metadata-Version: 2.4
Name: streamlit-session-memo
Version: 0.3.2
Author-email: "Yuichiro Tachibana (Tsuchiya)" <t.yic.yt@gmail.com>
License-Expression: MIT
License-File: LICENSE
Requires-Python: !=3.9.7,>=3.9
Requires-Dist: streamlit>=1.0.0
